{
    "id": "dbt-labs/audit_helper/0.2.0",
    "name": "audit_helper",
    "version": "0.2.0",
    "published_at": "2020-07-31T15:03:05.795835+00:00",
    "packages": [
        {
            "package": "dbt-labs/dbt_utils",
            "version": [
                ">=0.1.24",
                "<0.6.0"
            ]
        }
    ],
    "works_with": [],
    "_source": {
        "type": "github",
        "url": "https://github.com/dbt-labs/dbt-audit-helper/tree/0.2.0/",
        "readme": "https://raw.githubusercontent.com/dbt-labs/dbt-audit-helper/0.2.0/README.md"
    },
    "downloads": {
        "tarball": "https://codeload.github.com/dbt-labs/dbt-audit-helper/tar.gz/0.2.0",
        "format": "tgz",
        "sha1": "27122069f1bc1a9f86768c26253c536f0073854f"
    }
}
