{
    "id": "fivetran/facebook_ads_creative_history/v0.2.2",
    "name": "facebook_ads_creative_history",
    "version": "v0.2.2",
    "published_at": "2021-05-03T15:02:48.897912+00:00",
    "packages": [
        {
            "package": "fivetran/facebook_ads_source",
            "version": [
                ">=0.2.0",
                "<0.3.0"
            ]
        }
    ],
    "works_with": [],
    "_source": {
        "type": "github",
        "url": "https://github.com/fivetran/dbt_facebook_ads_creative_history/tree/v0.2.2/",
        "readme": "https://raw.githubusercontent.com/fivetran/dbt_facebook_ads_creative_history/v0.2.2/README.md"
    },
    "downloads": {
        "tarball": "https://codeload.github.com/fivetran/dbt_facebook_ads_creative_history/tar.gz/v0.2.2",
        "format": "tgz",
        "sha1": "c59975f9663098770c5857f21677a5c07ee1995c"
    }
}