{
    "id": "Montreal-Analytics/snowflake_utils/0.2.0",
    "name": "snowflake_utils",
    "version": "0.2.0",
    "published_at": "1970-01-01T00:00:00.000000+00:00",
    "packages": [
        {
            "package": "fishtown-analytics/dbt_utils",
            "version": ">=0.1.25"
        }
    ],
    "require_dbt_version": ">=0.17.0",
    "works_with": [],
    "_source": {
        "type": "github",
        "url": "https://github.com/Montreal-Analytics/dbt-snowflake-utils/tree/0.2.0/",
        "readme": "https://raw.githubusercontent.com/Montreal-Analytics/dbt-snowflake-utils/0.2.0/README.md"
    },
    "downloads": {
        "tarball": "https://codeload.github.com/Montreal-Analytics/dbt-snowflake-utils/tar.gz/0.2.0",
        "format": "tgz",
        "sha1": "d22af236b101b6078268993b8fe5882f509ac34e"
    }
}