{
    "id": "fivetran/stripe_source/v0.4.0",
    "name": "stripe_source",
    "version": "v0.4.0",
    "published_at": "2021-07-23T16:02:35.527468+00:00",
    "packages": [
        {
            "package": "fivetran/fivetran_utils",
            "version": [
                ">=0.2.0",
                "<0.3.0"
            ]
        }
    ],
    "works_with": [],
    "_source": {
        "type": "github",
        "url": "https://github.com/fivetran/dbt_stripe_source/tree/v0.4.0/",
        "readme": "https://raw.githubusercontent.com/fivetran/dbt_stripe_source/v0.4.0/README.md"
    },
    "downloads": {
        "tarball": "https://codeload.github.com/fivetran/dbt_stripe_source/tar.gz/v0.4.0",
        "format": "tgz",
        "sha1": "6005189a5177782df8c2f3cd7c80d35c63771895"
    }
}