{
    "id": "fivetran/hubspot_source/v0.4.1",
    "name": "hubspot_source",
    "version": "v0.4.1",
    "published_at": "2021-07-29T20:03:28.030376+00:00",
    "packages": [
        {
            "package": "fivetran/fivetran_utils",
            "version": [
                ">=0.2.0",
                "<0.3.0"
            ]
        }
    ],
    "works_with": [],
    "_source": {
        "type": "github",
        "url": "https://github.com/fivetran/dbt_hubspot_source/tree/v0.4.1/",
        "readme": "https://raw.githubusercontent.com/fivetran/dbt_hubspot_source/v0.4.1/README.md"
    },
    "downloads": {
        "tarball": "https://codeload.github.com/fivetran/dbt_hubspot_source/tar.gz/v0.4.1",
        "format": "tgz",
        "sha1": "20e7ea84eb43d35604d91423413676dcd5f6b413"
    }
}