{
    "id": "snowplow/snowplow_ecommerce/0.8.2",
    "name": "snowplow_ecommerce",
    "version": "0.8.2",
    "published_at": "1970-01-01T00:00:00.000000+00:00",
    "packages": [
        {
            "package": "snowplow/snowplow_utils",
            "version": [
                ">=0.16.3",
                "<0.17.0"
            ]
        }
    ],
    "require_dbt_version": [
        ">=1.5.0",
        "<2.0.0"
    ],
    "works_with": [],
    "_source": {
        "type": "github",
        "url": "https://github.com/snowplow/dbt-snowplow-ecommerce/tree/0.8.2/",
        "readme": "https://raw.githubusercontent.com/snowplow/dbt-snowplow-ecommerce/0.8.2/README.md"
    },
    "downloads": {
        "tarball": "https://codeload.github.com/snowplow/dbt-snowplow-ecommerce/tar.gz/0.8.2",
        "format": "tgz",
        "sha1": "c8ca58a9b2893cd578b23ec3ca150b1808d1e776"
    },
    "fusion_compatibility": {
        "version": "0.8.2",
        "require_dbt_version_defined": true,
        "require_dbt_version_compatible": false,
        "parse_compatible": false,
        "parse_compatibility_result": {
            "parse_exit_code": 1,
            "total_errors": 29,
            "total_warnings": 2,
            "errors": [
                {
                    "body": "Invalid model definition `snowplow_ecommerce.products.scratch.databricks`: Failed to eval the compiled Jinja expression invalid operation: cannot perform a containment check on this value\n(in dbt_project.yml:138:1)\n  --> dbt_project.yml:138:21",
                    "error_code": 1501,
                    "severity_text": "ERROR",
                    "original_severity_text": "ERROR"
                },
                {
                    "body": "Invalid model definition `snowplow_ecommerce.products.scratch.default`: Failed to eval the compiled Jinja expression invalid operation: cannot perform a containment check on this value\n(in dbt_project.yml:140:1)\n  --> dbt_project.yml:140:21",
                    "error_code": 1501,
                    "severity_text": "ERROR",
                    "original_severity_text": "ERROR"
                },
                {
                    "body": "While parsing config: Ignored unexpected key `\"tags\"`. YAML path: `columns[0].tags`.\n  --> models/base/manifest/base_manifest.yml:41:9",
                    "error_code": 1060,
                    "severity_text": "ERROR",
                    "original_severity_text": "ERROR"
                },
                {
                    "body": "While parsing config: Ignored unexpected key `\"tags\"`. YAML path: `columns[0].tags`.\n  --> models/base/manifest/base_manifest.yml:9:9",
                    "error_code": 1060,
                    "severity_text": "ERROR",
                    "original_severity_text": "ERROR"
                },
                {
                    "body": "Ignored unexpected key `\"snowplow_optimize\"`. YAML path: `snowplow_optimize`.\n  --> models/base/manifest/snowplow_ecommerce_base_sessions_lifecycle_manifest.sql:1:1",
                    "error_code": 1060,
                    "severity_text": "ERROR",
                    "original_severity_text": "ERROR"
                },
                {
                    "body": "Ignored unexpected key `\"upsert_date_key\"`. YAML path: `upsert_date_key`.\n  --> models/base/manifest/snowplow_ecommerce_base_sessions_lifecycle_manifest.sql:1:1",
                    "error_code": 1060,
                    "severity_text": "ERROR",
                    "original_severity_text": "ERROR"
                },
                {
                    "body": "While parsing config: Ignored unexpected key `\"tags\"`. YAML path: `columns[0].tags`.\n  --> models/base/manifest/base_manifest.yml:29:9",
                    "error_code": 1060,
                    "severity_text": "ERROR",
                    "original_severity_text": "ERROR"
                },
                {
                    "body": "While parsing config: Ignored unexpected key `\"tags\"`. YAML path: `columns[0].tags`.\n  --> models/base/scratch/base_scratch.yml:16:9",
                    "error_code": 1060,
                    "severity_text": "ERROR",
                    "original_severity_text": "ERROR"
                },
                {
                    "body": "While parsing config: Ignored unexpected key `\"tags\"`. YAML path: `columns[0].tags`.\n  --> models/carts/scratch/carts_scratch.yml:9:9",
                    "error_code": 1060,
                    "severity_text": "ERROR",
                    "original_severity_text": "ERROR"
                },
                {
                    "body": "While parsing config: Ignored unexpected key `\"tags\"`. YAML path: `columns[0].tags`.\n  --> models/carts/carts.yml:9:9",
                    "error_code": 1060,
                    "severity_text": "ERROR",
                    "original_severity_text": "ERROR"
                },
                {
                    "body": "Ignored unexpected key `\"snowplow_optimize\"`. YAML path: `snowplow_optimize`.\n  --> models/carts/snowplow_ecommerce_cart_interactions.sql:1:1",
                    "error_code": 1060,
                    "severity_text": "ERROR",
                    "original_severity_text": "ERROR"
                },
                {
                    "body": "Ignored unexpected key `\"upsert_date_key\"`. YAML path: `upsert_date_key`.\n  --> models/carts/snowplow_ecommerce_cart_interactions.sql:1:1",
                    "error_code": 1060,
                    "severity_text": "ERROR",
                    "original_severity_text": "ERROR"
                },
                {
                    "body": "While parsing config: Ignored unexpected key `\"tags\"`. YAML path: `columns[0].tags`.\n  --> models/checkouts/scratch/checkouts_scratch.yml:9:9",
                    "error_code": 1060,
                    "severity_text": "ERROR",
                    "original_severity_text": "ERROR"
                },
                {
                    "body": "While parsing config: Ignored unexpected key `\"tags\"`. YAML path: `columns[0].tags`.\n  --> models/checkouts/checkouts.yml:9:9",
                    "error_code": 1060,
                    "severity_text": "ERROR",
                    "original_severity_text": "ERROR"
                },
                {
                    "body": "Ignored unexpected key `\"snowplow_optimize\"`. YAML path: `snowplow_optimize`.\n  --> models/checkouts/snowplow_ecommerce_checkout_interactions.sql:1:1",
                    "error_code": 1060,
                    "severity_text": "ERROR",
                    "original_severity_text": "ERROR"
                },
                {
                    "body": "Ignored unexpected key `\"upsert_date_key\"`. YAML path: `upsert_date_key`.\n  --> models/checkouts/snowplow_ecommerce_checkout_interactions.sql:1:1",
                    "error_code": 1060,
                    "severity_text": "ERROR",
                    "original_severity_text": "ERROR"
                },
                {
                    "body": "While parsing config: Ignored unexpected key `\"tags\"`. YAML path: `columns[0].tags`.\n  --> models/products/scratch/products_scratch.yml:9:9",
                    "error_code": 1060,
                    "severity_text": "ERROR",
                    "original_severity_text": "ERROR"
                },
                {
                    "body": "While parsing config: Ignored unexpected key `\"tags\"`. YAML path: `columns[0].tags`.\n  --> models/products/products.yml:9:9",
                    "error_code": 1060,
                    "severity_text": "ERROR",
                    "original_severity_text": "ERROR"
                },
                {
                    "body": "Ignored unexpected key `\"snowplow_optimize\"`. YAML path: `snowplow_optimize`.\n  --> models/products/snowplow_ecommerce_product_interactions.sql:1:1",
                    "error_code": 1060,
                    "severity_text": "ERROR",
                    "original_severity_text": "ERROR"
                },
                {
                    "body": "Ignored unexpected key `\"upsert_date_key\"`. YAML path: `upsert_date_key`.\n  --> models/products/snowplow_ecommerce_product_interactions.sql:1:1",
                    "error_code": 1060,
                    "severity_text": "ERROR",
                    "original_severity_text": "ERROR"
                },
                {
                    "body": "While parsing config: Ignored unexpected key `\"tags\"`. YAML path: `columns[0].tags`.\n  --> models/sessions/scratch/ecommerce_sessions_scratch.yml:9:9",
                    "error_code": 1060,
                    "severity_text": "ERROR",
                    "original_severity_text": "ERROR"
                },
                {
                    "body": "While parsing config: Ignored unexpected key `\"tags\"`. YAML path: `columns[0].tags`.\n  --> models/sessions/ecommerce_sessions.yml:9:9",
                    "error_code": 1060,
                    "severity_text": "ERROR",
                    "original_severity_text": "ERROR"
                },
                {
                    "body": "Ignored unexpected key `\"snowplow_optimize\"`. YAML path: `snowplow_optimize`.\n  --> models/sessions/snowplow_ecommerce_sessions.sql:1:1",
                    "error_code": 1060,
                    "severity_text": "ERROR",
                    "original_severity_text": "ERROR"
                },
                {
                    "body": "Ignored unexpected key `\"upsert_date_key\"`. YAML path: `upsert_date_key`.\n  --> models/sessions/snowplow_ecommerce_sessions.sql:1:1",
                    "error_code": 1060,
                    "severity_text": "ERROR",
                    "original_severity_text": "ERROR"
                },
                {
                    "body": "While parsing config: Ignored unexpected key `\"tags\"`. YAML path: `columns[0].tags`.\n  --> models/transactions/scratch/transactions_scratch.yml:9:9",
                    "error_code": 1060,
                    "severity_text": "ERROR",
                    "original_severity_text": "ERROR"
                },
                {
                    "body": "While parsing config: Ignored unexpected key `\"tags\"`. YAML path: `columns[0].tags`.\n  --> models/transactions/transactions.yml:9:9",
                    "error_code": 1060,
                    "severity_text": "ERROR",
                    "original_severity_text": "ERROR"
                },
                {
                    "body": "Ignored unexpected key `\"snowplow_optimize\"`. YAML path: `snowplow_optimize`.\n  --> models/transactions/snowplow_ecommerce_transaction_interactions.sql:1:1",
                    "error_code": 1060,
                    "severity_text": "ERROR",
                    "original_severity_text": "ERROR"
                },
                {
                    "body": "Ignored unexpected key `\"upsert_date_key\"`. YAML path: `upsert_date_key`.\n  --> models/transactions/snowplow_ecommerce_transaction_interactions.sql:1:1",
                    "error_code": 1060,
                    "severity_text": "ERROR",
                    "original_severity_text": "ERROR"
                },
                {
                    "body": "Found duplicate model 'snowplow_ecommerce_product_interactions_this_run'\n  --> models/products/scratch/default/snowplow_ecommerce_product_interactions_this_run.sql",
                    "error_code": 1005,
                    "severity_text": "ERROR",
                    "original_severity_text": "ERROR"
                }
            ],
            "warnings": [],
            "fusion_version": "2.0.0-preview.110"
        },
        "manually_verified_compatible": false,
        "manually_verified_incompatible": false,
        "download_failed": false,
        "fusion_compatible_download": {}
    }
}