{
    "id": "fivetran/tiktok_ads/v0.1.0",
    "name": "tiktok_ads",
    "version": "v0.1.0",
    "published_at": "1970-01-01T00:00:00.000000+00:00",
    "packages": [
        {
            "git": "https://github.com/fivetran/dbt_tiktok_ads_source.git",
            "revision": "main",
            "warn-unpinned": false
        }
    ],
    "require_dbt_version": [
        ">=1.0.0",
        "<2.0.0"
    ],
    "works_with": [],
    "_source": {
        "type": "github",
        "url": "https://github.com/fivetran/dbt_tiktok_ads/tree/v0.1.0/",
        "readme": "https://raw.githubusercontent.com/fivetran/dbt_tiktok_ads/v0.1.0/README.md"
    },
    "downloads": {
        "tarball": "https://codeload.github.com/fivetran/dbt_tiktok_ads/tar.gz/v0.1.0",
        "format": "tgz",
        "sha1": "48c1dd995d868978c101a3a26c28eaed31d72427"
    }
}