{
    "id": "fishtown-analytics/adwords/0.1.3",
    "name": "adwords",
    "version": "0.1.3",
    "published_at": "2018-11-28T16:16:06.455784-05:00",
    "packages": [],
    "works_with": [],
    "_source": {
        "type": "github",
        "url": "https://github.com/fishtown-analytics/adwords/tree/0.1.3/",
        "readme": "https://raw.githubusercontent.com/fishtown-analytics/adwords/0.1.3/README.md"
    },
    "downloads": {
        "tarball": "https://github.com/fishtown-analytics/adwords/archive/0.1.3.tar.gz",
        "format": "tgz",
        "sha1": "f2ca259724618d17f5bd76b464387d48d783b756"
    }
}