{
    "id": "snowplow/snowplow_unified/0.4.1",
    "name": "snowplow_unified",
    "version": "0.4.1",
    "published_at": "1970-01-01T00:00:00.000000+00:00",
    "packages": [
        {
            "package": "snowplow/snowplow_utils",
            "version": [
                ">=0.16.2",
                "<0.17.0"
            ]
        }
    ],
    "require_dbt_version": [
        ">=1.6.0",
        "<2.0.0"
    ],
    "works_with": [],
    "_source": {
        "type": "github",
        "url": "https://github.com/snowplow/dbt-snowplow-unified/tree/0.4.1/",
        "readme": "https://raw.githubusercontent.com/snowplow/dbt-snowplow-unified/0.4.1/README.md"
    },
    "downloads": {
        "tarball": "https://codeload.github.com/snowplow/dbt-snowplow-unified/tar.gz/0.4.1",
        "format": "tgz",
        "sha1": "88571b2d91cd28aafea1df18ef22827952234499"
    },
    "fusion_compatibility": {
        "version": "0.4.1",
        "require_dbt_version_defined": true,
        "require_dbt_version_compatible": false,
        "parse_compatible": false,
        "parse_compatibility_result": {
            "parse_exit_code": 1,
            "total_errors": 38,
            "total_warnings": 1,
            "errors": [
                {
                    "body": "While parsing config: Ignored unexpected key `\"tags\"`. YAML path: `columns[0].tags`.\n  --> models/base/manifest/base_manifest.yml:41:9",
                    "error_code": 1060,
                    "severity_text": "ERROR",
                    "dbt_core_event_code": "",
                    "original_severity_text": "ERROR"
                },
                {
                    "body": "While parsing config: Ignored unexpected key `\"tags\"`. YAML path: `columns[0].tags`.\n  --> models/base/manifest/base_manifest.yml:9:9",
                    "error_code": 1060,
                    "severity_text": "ERROR",
                    "dbt_core_event_code": "",
                    "original_severity_text": "ERROR"
                },
                {
                    "body": "Ignored unexpected key `\"snowplow_optimize\"`. YAML path: `snowplow_optimize`.\n  --> models/base/manifest/snowplow_unified_base_sessions_lifecycle_manifest.sql:1:1",
                    "error_code": 1060,
                    "severity_text": "ERROR",
                    "dbt_core_event_code": "",
                    "original_severity_text": "ERROR"
                },
                {
                    "body": "Ignored unexpected key `\"upsert_date_key\"`. YAML path: `upsert_date_key`.\n  --> models/base/manifest/snowplow_unified_base_sessions_lifecycle_manifest.sql:1:1",
                    "error_code": 1060,
                    "severity_text": "ERROR",
                    "dbt_core_event_code": "",
                    "original_severity_text": "ERROR"
                },
                {
                    "body": "While parsing config: Ignored unexpected key `\"tags\"`. YAML path: `columns[0].tags`.\n  --> models/base/manifest/base_manifest.yml:29:9",
                    "error_code": 1060,
                    "severity_text": "ERROR",
                    "dbt_core_event_code": "",
                    "original_severity_text": "ERROR"
                },
                {
                    "body": "While parsing config: Ignored unexpected key `\"tags\"`. YAML path: `columns[6].tags`.\n  --> models/base/scratch/base_scratch.yml:44:9",
                    "error_code": 1060,
                    "severity_text": "ERROR",
                    "dbt_core_event_code": "",
                    "original_severity_text": "ERROR"
                },
                {
                    "body": "While parsing config: Ignored unexpected key `\"tags\"`. YAML path: `columns[0].tags`.\n  --> models/base/scratch/base_scratch.yml:16:9",
                    "error_code": 1060,
                    "severity_text": "ERROR",
                    "dbt_core_event_code": "",
                    "original_severity_text": "ERROR"
                },
                {
                    "body": "While parsing config: Ignored unexpected key `\"tags\"`. YAML path: `columns[7].tags`.\n  --> models/base/scratch/base_scratch.yml:465:9",
                    "error_code": 1060,
                    "severity_text": "ERROR",
                    "dbt_core_event_code": "",
                    "original_severity_text": "ERROR"
                },
                {
                    "body": "While parsing config: Ignored unexpected key `\"tags\"`. YAML path: `columns[0].tags`.\n  --> models/optional_modules/app_errors/scratch/app_errors_scratch.yml:9:9",
                    "error_code": 1060,
                    "severity_text": "ERROR",
                    "dbt_core_event_code": "",
                    "original_severity_text": "ERROR"
                },
                {
                    "body": "While parsing config: Ignored unexpected key `\"tags\"`. YAML path: `columns[0].tags`.\n  --> models/optional_modules/app_errors/app_errors.yml:9:9",
                    "error_code": 1060,
                    "severity_text": "ERROR",
                    "dbt_core_event_code": "",
                    "original_severity_text": "ERROR"
                },
                {
                    "body": "Ignored unexpected key `\"snowplow_optimize\"`. YAML path: `snowplow_optimize`.\n  --> models/optional_modules/app_errors/snowplow_unified_app_errors.sql:1:1",
                    "error_code": 1060,
                    "severity_text": "ERROR",
                    "dbt_core_event_code": "",
                    "original_severity_text": "ERROR"
                },
                {
                    "body": "Ignored unexpected key `\"upsert_date_key\"`. YAML path: `upsert_date_key`.\n  --> models/optional_modules/app_errors/snowplow_unified_app_errors.sql:1:1",
                    "error_code": 1060,
                    "severity_text": "ERROR",
                    "dbt_core_event_code": "",
                    "original_severity_text": "ERROR"
                },
                {
                    "body": "Ignored unexpected key `\"snowplow_optimize\"`. YAML path: `snowplow_optimize`.\n  --> models/optional_modules/consent/snowplow_unified_consent_log.sql:1:1",
                    "error_code": 1060,
                    "severity_text": "ERROR",
                    "dbt_core_event_code": "",
                    "original_severity_text": "ERROR"
                },
                {
                    "body": "Ignored unexpected key `\"upsert_date_key\"`. YAML path: `upsert_date_key`.\n  --> models/optional_modules/consent/snowplow_unified_consent_log.sql:1:1",
                    "error_code": 1060,
                    "severity_text": "ERROR",
                    "dbt_core_event_code": "",
                    "original_severity_text": "ERROR"
                },
                {
                    "body": "While parsing config: Ignored unexpected key `\"describtion\"`. YAML path: `columns[14].describtion`.\n  --> models/optional_modules/consent/consent.yml:124:9",
                    "error_code": 1060,
                    "severity_text": "ERROR",
                    "dbt_core_event_code": "",
                    "original_severity_text": "ERROR"
                },
                {
                    "body": "While parsing config: Ignored unexpected key `\"tags\"`. YAML path: `columns[0].tags`.\n  --> models/optional_modules/conversions/conversions.yml:9:9",
                    "error_code": 1060,
                    "severity_text": "ERROR",
                    "dbt_core_event_code": "",
                    "original_severity_text": "ERROR"
                },
                {
                    "body": "While parsing config: Ignored unexpected key `\"tags\"`. YAML path: `columns[0].tags`.\n  --> models/optional_modules/conversions/conversions.yml:51:9",
                    "error_code": 1060,
                    "severity_text": "ERROR",
                    "dbt_core_event_code": "",
                    "original_severity_text": "ERROR"
                },
                {
                    "body": "Ignored unexpected key `\"snowplow_optimize\"`. YAML path: `snowplow_optimize`.\n  --> models/optional_modules/conversions/snowplow_unified_conversions.sql:1:1",
                    "error_code": 1060,
                    "severity_text": "ERROR",
                    "dbt_core_event_code": "",
                    "original_severity_text": "ERROR"
                },
                {
                    "body": "Ignored unexpected key `\"upsert_date_key\"`. YAML path: `upsert_date_key`.\n  --> models/optional_modules/conversions/snowplow_unified_conversions.sql:1:1",
                    "error_code": 1060,
                    "severity_text": "ERROR",
                    "dbt_core_event_code": "",
                    "original_severity_text": "ERROR"
                },
                {
                    "body": "Ignored unexpected key `\"snowplow_optimize\"`. YAML path: `snowplow_optimize`.\n  --> models/optional_modules/core_web_vitals/snowplow_unified_web_vitals.sql:1:1",
                    "error_code": 1060,
                    "severity_text": "ERROR",
                    "dbt_core_event_code": "",
                    "original_severity_text": "ERROR"
                },
                {
                    "body": "Ignored unexpected key `\"upsert_date_key\"`. YAML path: `upsert_date_key`.\n  --> models/optional_modules/core_web_vitals/snowplow_unified_web_vitals.sql:1:1",
                    "error_code": 1060,
                    "severity_text": "ERROR",
                    "dbt_core_event_code": "",
                    "original_severity_text": "ERROR"
                },
                {
                    "body": "While parsing config: Ignored unexpected key `\"tags\"`. YAML path: `columns[2].tags`.\n  --> models/sessions/scratch/sessions_scratch.yml:12:9",
                    "error_code": 1060,
                    "severity_text": "ERROR",
                    "dbt_core_event_code": "",
                    "original_severity_text": "ERROR"
                },
                {
                    "body": "While parsing config: Ignored unexpected key `\"tags\"`. YAML path: `columns[1].tags`.\n  --> models/sessions/sessions.yml:10:9",
                    "error_code": 1060,
                    "severity_text": "ERROR",
                    "dbt_core_event_code": "",
                    "original_severity_text": "ERROR"
                },
                {
                    "body": "Ignored unexpected key `\"snowplow_optimize\"`. YAML path: `snowplow_optimize`.\n  --> models/sessions/snowplow_unified_sessions.sql:1:1",
                    "error_code": 1060,
                    "severity_text": "ERROR",
                    "dbt_core_event_code": "",
                    "original_severity_text": "ERROR"
                },
                {
                    "body": "Ignored unexpected key `\"upsert_date_key\"`. YAML path: `upsert_date_key`.\n  --> models/sessions/snowplow_unified_sessions.sql:1:1",
                    "error_code": 1060,
                    "severity_text": "ERROR",
                    "dbt_core_event_code": "",
                    "original_severity_text": "ERROR"
                },
                {
                    "body": "While parsing config: Ignored unexpected key `\"tags\"`. YAML path: `columns[0].tags`.\n  --> models/user_mapping/user_mapping.yml:9:9",
                    "error_code": 1060,
                    "severity_text": "ERROR",
                    "dbt_core_event_code": "",
                    "original_severity_text": "ERROR"
                },
                {
                    "body": "While parsing config: Ignored unexpected key `\"tags\"`. YAML path: `columns[0].tags`.\n  --> models/users/scratch/users_scratch.yml:142:9",
                    "error_code": 1060,
                    "severity_text": "ERROR",
                    "dbt_core_event_code": "",
                    "original_severity_text": "ERROR"
                },
                {
                    "body": "While parsing config: Ignored unexpected key `\"tags\"`. YAML path: `columns[0].tags`.\n  --> models/users/scratch/users_scratch.yml:152:9",
                    "error_code": 1060,
                    "severity_text": "ERROR",
                    "dbt_core_event_code": "",
                    "original_severity_text": "ERROR"
                },
                {
                    "body": "While parsing config: Ignored unexpected key `\"tags\"`. YAML path: `columns[0].tags`.\n  --> models/users/scratch/users_scratch.yml:162:9",
                    "error_code": 1060,
                    "severity_text": "ERROR",
                    "dbt_core_event_code": "",
                    "original_severity_text": "ERROR"
                },
                {
                    "body": "While parsing config: Ignored unexpected key `\"tags\"`. YAML path: `columns[1].tags`.\n  --> models/users/scratch/users_scratch.yml:11:9",
                    "error_code": 1060,
                    "severity_text": "ERROR",
                    "dbt_core_event_code": "",
                    "original_severity_text": "ERROR"
                },
                {
                    "body": "While parsing config: Ignored unexpected key `\"tags\"`. YAML path: `columns[1].tags`.\n  --> models/users/users.yml:11:9",
                    "error_code": 1060,
                    "severity_text": "ERROR",
                    "dbt_core_event_code": "",
                    "original_severity_text": "ERROR"
                },
                {
                    "body": "Ignored unexpected key `\"disable_upsert_lookback\"`. YAML path: `disable_upsert_lookback`.\n  --> models/users/snowplow_unified_users.sql:1:1",
                    "error_code": 1060,
                    "severity_text": "ERROR",
                    "dbt_core_event_code": "",
                    "original_severity_text": "ERROR"
                },
                {
                    "body": "Ignored unexpected key `\"snowplow_optimize\"`. YAML path: `snowplow_optimize`.\n  --> models/users/snowplow_unified_users.sql:1:1",
                    "error_code": 1060,
                    "severity_text": "ERROR",
                    "dbt_core_event_code": "",
                    "original_severity_text": "ERROR"
                },
                {
                    "body": "Ignored unexpected key `\"upsert_date_key\"`. YAML path: `upsert_date_key`.\n  --> models/users/snowplow_unified_users.sql:1:1",
                    "error_code": 1060,
                    "severity_text": "ERROR",
                    "dbt_core_event_code": "",
                    "original_severity_text": "ERROR"
                },
                {
                    "body": "While parsing config: Ignored unexpected key `\"tags\"`. YAML path: `columns[0].tags`.\n  --> models/views/scratch/views_scratch.yml:9:9",
                    "error_code": 1060,
                    "severity_text": "ERROR",
                    "dbt_core_event_code": "",
                    "original_severity_text": "ERROR"
                },
                {
                    "body": "While parsing config: Ignored unexpected key `\"tags\"`. YAML path: `columns[0].tags`.\n  --> models/views/views.yml:9:9",
                    "error_code": 1060,
                    "severity_text": "ERROR",
                    "dbt_core_event_code": "",
                    "original_severity_text": "ERROR"
                },
                {
                    "body": "Ignored unexpected key `\"snowplow_optimize\"`. YAML path: `snowplow_optimize`.\n  --> models/views/snowplow_unified_views.sql:1:1",
                    "error_code": 1060,
                    "severity_text": "ERROR",
                    "dbt_core_event_code": "",
                    "original_severity_text": "ERROR"
                },
                {
                    "body": "Ignored unexpected key `\"upsert_date_key\"`. YAML path: `upsert_date_key`.\n  --> models/views/snowplow_unified_views.sql:1:1",
                    "error_code": 1060,
                    "severity_text": "ERROR",
                    "dbt_core_event_code": "",
                    "original_severity_text": "ERROR"
                }
            ],
            "warnings": [],
            "fusion_version": "2.0.0-preview.101"
        },
        "manually_verified_compatible": false,
        "manually_verified_incompatible": false
    }
}