{
    "id": "Datavault-UK/dbtvault/v0.8.0",
    "name": "dbtvault",
    "version": "v0.8.0",
    "published_at": "2022-02-21T18:01:01.878510+00:00",
    "packages": [
        {
            "package": "dbt-labs/dbt_utils",
            "version": [
                ">=0.8.0",
                "<0.9.0"
            ]
        }
    ],
    "works_with": [],
    "_source": {
        "type": "github",
        "url": "https://github.com/Datavault-UK/dbtvault/tree/v0.8.0/",
        "readme": "https://raw.githubusercontent.com/Datavault-UK/dbtvault/v0.8.0/README.md"
    },
    "downloads": {
        "tarball": "https://codeload.github.com/Datavault-UK/dbtvault/tar.gz/v0.8.0",
        "format": "tgz",
        "sha1": "3d9c4bee7520e2c5bda171296379e209e4a48371"
    }
}