{
    "id": "fishtown-analytics/facebook-ads/0.2.6",
    "name": "facebook-ads",
    "version": "0.2.6",
    "published_at": "2018-11-28T16:16:06.455784-05:00",
    "packages": [],
    "works_with": [],
    "_source": {
        "type": "github",
        "url": "https://github.com/fishtown-analytics/facebook-ads/tree/0.2.6/",
        "readme": "https://raw.githubusercontent.com/fishtown-analytics/facebook-ads/0.2.6/README.md"
    },
    "downloads": {
        "tarball": "https://codeload.github.com/fishtown-analytics/facebook-ads/tar.gz/0.2.6",
        "format": "tgz",
        "sha1": "e29b91a4efec90188d49d0b34e2617f0fd354d65"
    }
}