{
    "id": "fivetran/zendesk_source/v0.1.0",
    "name": "zendesk_source",
    "version": "v0.1.0",
    "published_at": "2020-09-15T00:04:36.999415+00:00",
    "packages": [
        {
            "package": "fishtown-analytics/dbt_utils",
            "version": [
                ">=0.6.0",
                "<0.7.0"
            ]
        }
    ],
    "works_with": [],
    "_source": {
        "type": "github",
        "url": "https://github.com/fivetran/dbt_zendesk_source/tree/v0.1.0/",
        "readme": "https://raw.githubusercontent.com/fivetran/dbt_zendesk_source/v0.1.0/README.md"
    },
    "downloads": {
        "tarball": "https://codeload.github.com/fivetran/dbt_zendesk_source/tar.gz/v0.1.0",
        "format": "tgz",
        "sha1": "855c94253a6de89ab4926c7afaeb61bca8721cc0"
    }
}