{
    "id": "fishtown-analytics/bing_ads/0.1.5",
    "name": "bing_ads",
    "version": "0.1.5",
    "published_at": "2019-03-20T14:00:02.890252+00:00",
    "packages": [
        {
            "package": "fishtown-analytics/dbt_utils",
            "version": ">=0.1.20"
        }
    ],
    "works_with": [],
    "_source": {
        "type": "github",
        "url": "https://github.com/fishtown-analytics/bing-ads/tree/0.1.5/",
        "readme": "https://raw.githubusercontent.com/fishtown-analytics/bing-ads/0.1.5/README.md"
    },
    "downloads": {
        "tarball": "https://codeload.github.com/fishtown-analytics/bing-ads/tar.gz/0.1.5",
        "format": "tgz",
        "sha1": "8ec04d5674744d5f63c959fe8f34fda33d8f7813"
    }
}