{
    "id": "datalakehouse/dlh_xero/0.1.1",
    "name": "dlh_xero",
    "version": "0.1.1",
    "published_at": "1970-01-01T00:00:00.000000+00:00",
    "packages": [],
    "require_dbt_version": ">=0.21.0",
    "works_with": [],
    "_source": {
        "type": "github",
        "url": "https://github.com/datalakehouse/dlh-xero-analytics-dbt/tree/0.1.1/",
        "readme": "https://raw.githubusercontent.com/datalakehouse/dlh-xero-analytics-dbt/0.1.1/README.md"
    },
    "downloads": {
        "tarball": "https://codeload.github.com/datalakehouse/dlh-xero-analytics-dbt/tar.gz/0.1.1",
        "format": "tgz",
        "sha1": "36c443b01318bfc70c2f5d347317490300f6108a"
    },
    "fusion_compatibility": {
        "version": "0.1.1",
        "require_dbt_version_defined": true,
        "require_dbt_version_compatible": true,
        "parse_compatible": false,
        "parse_compatibility_result": {
            "parse_exit_code": 1,
            "total_errors": 11,
            "total_warnings": 1,
            "errors": [
                {
                    "body": "Deprecated test arguments: [\"field\", \"to\"] at top-level detected. Please migrate to the new format under the 'arguments' field: https://docs.getdbt.com/reference/deprecations#missingargumentspropertyingenerictestdeprecation.\n  --> ../../../../../../private/var/folders/xf/r3bz6sxx0m57976q8nb2d1fh0000gp/T/tmp_ulib0nz/models/schema.yml:58:22",
                    "error_code": 102,
                    "severity_text": "ERROR",
                    "dbt_core_event_code": "",
                    "original_severity_text": "ERROR"
                },
                {
                    "body": "Deprecated test arguments: [\"field\", \"to\"] at top-level detected. Please migrate to the new format under the 'arguments' field: https://docs.getdbt.com/reference/deprecations#missingargumentspropertyingenerictestdeprecation.\n  --> ../../../../../../private/var/folders/xf/r3bz6sxx0m57976q8nb2d1fh0000gp/T/tmp_ulib0nz/models/schema.yml:70:22",
                    "error_code": 102,
                    "severity_text": "ERROR",
                    "dbt_core_event_code": "",
                    "original_severity_text": "ERROR"
                },
                {
                    "body": "Deprecated test arguments: [\"field\", \"to\"] at top-level detected. Please migrate to the new format under the 'arguments' field: https://docs.getdbt.com/reference/deprecations#missingargumentspropertyingenerictestdeprecation.\n  --> ../../../../../../private/var/folders/xf/r3bz6sxx0m57976q8nb2d1fh0000gp/T/tmp_ulib0nz/models/schema.yml:64:22",
                    "error_code": 102,
                    "severity_text": "ERROR",
                    "dbt_core_event_code": "",
                    "original_severity_text": "ERROR"
                },
                {
                    "body": "Deprecated test arguments: [\"field\", \"to\"] at top-level detected. Please migrate to the new format under the 'arguments' field: https://docs.getdbt.com/reference/deprecations#missingargumentspropertyingenerictestdeprecation.\n  --> ../../../../../../private/var/folders/xf/r3bz6sxx0m57976q8nb2d1fh0000gp/T/tmp_ulib0nz/models/schema.yml:94:22",
                    "error_code": 102,
                    "severity_text": "ERROR",
                    "dbt_core_event_code": "",
                    "original_severity_text": "ERROR"
                },
                {
                    "body": "Deprecated test arguments: [\"field\", \"to\"] at top-level detected. Please migrate to the new format under the 'arguments' field: https://docs.getdbt.com/reference/deprecations#missingargumentspropertyingenerictestdeprecation.\n  --> ../../../../../../private/var/folders/xf/r3bz6sxx0m57976q8nb2d1fh0000gp/T/tmp_ulib0nz/models/schema.yml:111:22",
                    "error_code": 102,
                    "severity_text": "ERROR",
                    "dbt_core_event_code": "",
                    "original_severity_text": "ERROR"
                },
                {
                    "body": "Deprecated test arguments: [\"field\", \"to\"] at top-level detected. Please migrate to the new format under the 'arguments' field: https://docs.getdbt.com/reference/deprecations#missingargumentspropertyingenerictestdeprecation.\n  --> ../../../../../../private/var/folders/xf/r3bz6sxx0m57976q8nb2d1fh0000gp/T/tmp_ulib0nz/models/schema.yml:128:22",
                    "error_code": 102,
                    "severity_text": "ERROR",
                    "dbt_core_event_code": "",
                    "original_severity_text": "ERROR"
                },
                {
                    "body": "Deprecated test arguments: [\"field\", \"to\"] at top-level detected. Please migrate to the new format under the 'arguments' field: https://docs.getdbt.com/reference/deprecations#missingargumentspropertyingenerictestdeprecation.\n  --> ../../../../../../private/var/folders/xf/r3bz6sxx0m57976q8nb2d1fh0000gp/T/tmp_ulib0nz/models/schema.yml:140:22",
                    "error_code": 102,
                    "severity_text": "ERROR",
                    "dbt_core_event_code": "",
                    "original_severity_text": "ERROR"
                },
                {
                    "body": "Deprecated test arguments: [\"field\", \"to\"] at top-level detected. Please migrate to the new format under the 'arguments' field: https://docs.getdbt.com/reference/deprecations#missingargumentspropertyingenerictestdeprecation.\n  --> ../../../../../../private/var/folders/xf/r3bz6sxx0m57976q8nb2d1fh0000gp/T/tmp_ulib0nz/models/schema.yml:134:22",
                    "error_code": 102,
                    "severity_text": "ERROR",
                    "dbt_core_event_code": "",
                    "original_severity_text": "ERROR"
                },
                {
                    "body": "Deprecated test arguments: [\"field\", \"to\"] at top-level detected. Please migrate to the new format under the 'arguments' field: https://docs.getdbt.com/reference/deprecations#missingargumentspropertyingenerictestdeprecation.\n  --> ../../../../../../private/var/folders/xf/r3bz6sxx0m57976q8nb2d1fh0000gp/T/tmp_ulib0nz/models/schema.yml:156:22",
                    "error_code": 102,
                    "severity_text": "ERROR",
                    "dbt_core_event_code": "",
                    "original_severity_text": "ERROR"
                },
                {
                    "body": "Deprecated test arguments: [\"field\", \"to\"] at top-level detected. Please migrate to the new format under the 'arguments' field: https://docs.getdbt.com/reference/deprecations#missingargumentspropertyingenerictestdeprecation.\n  --> ../../../../../../private/var/folders/xf/r3bz6sxx0m57976q8nb2d1fh0000gp/T/tmp_ulib0nz/models/schema.yml:168:22",
                    "error_code": 102,
                    "severity_text": "ERROR",
                    "dbt_core_event_code": "",
                    "original_severity_text": "ERROR"
                },
                {
                    "body": "Deprecated test arguments: [\"field\", \"to\"] at top-level detected. Please migrate to the new format under the 'arguments' field: https://docs.getdbt.com/reference/deprecations#missingargumentspropertyingenerictestdeprecation.\n  --> ../../../../../../private/var/folders/xf/r3bz6sxx0m57976q8nb2d1fh0000gp/T/tmp_ulib0nz/models/schema.yml:162:22",
                    "error_code": 102,
                    "severity_text": "ERROR",
                    "dbt_core_event_code": "",
                    "original_severity_text": "ERROR"
                }
            ],
            "warnings": []
        },
        "manually_verified_compatible": false,
        "manually_verified_incompatible": false,
        "fusion_version_tested": "2.0.0-preview.89"
    }
}