{
    "id": "fivetran/twitter_ads/v0.2.2",
    "name": "twitter_ads",
    "version": "v0.2.2",
    "published_at": "2021-07-21T21:03:25.452187+00:00",
    "packages": [
        {
            "package": "fivetran/twitter_ads_source",
            "version": [
                ">=0.2.0",
                "<0.3.0"
            ]
        }
    ],
    "works_with": [],
    "_source": {
        "type": "github",
        "url": "https://github.com/fivetran/dbt_twitter/tree/v0.2.2/",
        "readme": "https://raw.githubusercontent.com/fivetran/dbt_twitter/v0.2.2/README.md"
    },
    "downloads": {
        "tarball": "https://codeload.github.com/fivetran/dbt_twitter/tar.gz/v0.2.2",
        "format": "tgz",
        "sha1": "397a65ef63ffe4d8bb94b6d557f1b5422f03680a"
    }
}